gondor/__init__.py
gondor/__main__.py
gondor/api.py
gondor/http.py
gondor/prettytable.py
gondor/progressbar.py
gondor/run.py
gondor/utils.py
gondor/yaml-py2-3.10.zip
gondor/yaml-py3-3.10.zip
gondor/ssl/gondor.io.crt
gondor/ssl/run.gondor.io.crt
gondor-1.2.6.dist-info/DESCRIPTION.rst
gondor-1.2.6.dist-info/entry_points.txt
gondor-1.2.6.dist-info/METADATA
gondor-1.2.6.dist-info/metadata.json
gondor-1.2.6.dist-info/RECORD
gondor-1.2.6.dist-info/top_level.txt
gondor-1.2.6.dist-info/WHEEL
