Metadata-Version: 2.0
Name: gondor
Version: 1.2.6
Summary: official gondor.io command line client
Home-page: https://github.com/eldarion/gondor-client
Author: Eldarion
Author-email: development@eldarion.com
License: UNKNOWN
Platform: UNKNOWN
Classifier: Programming Language :: Python
Classifier: Programming Language :: Python :: 3
Requires-Dist: six (>=1.3.0)
